{
  "updated": "2026-05-14T09:48:02.902Z",
  "channels": [
    {
      "name": "경제사냥꾼",
      "icon": "🎯",
      "videoId": "JdFcGLBI0U8",
      "summary": "[ 핵심 요약 ]\n\n- 트럼프가 젠슨 황을 직접 전화로 부른 것은 반도체 정책의 실용주의로의 전환을 의미하며 강경파 주도의 절대 차단에서 선택적 개방으로 전략이 변경되었음을 시사\n\n- 지난 6개월간 중국의 H200 수입 차단과 엔비디아 중국 점유율 0% 추락 속에서도 정부 간 협상의 여지가 생겼으며 이는 중간 성능 칩 수출 승인 시점 단축이나 차세대 규제 경로 명확화 수준의 실질적 진전을 가능하게 함\n\n- 반도체 밸류체인 전체에 선택적 개방이 확대되면서 SK 하이닉스와 삼성전자의 HBM 수요가 증가할 가능성이 높아졌으며 중국 국산 AI 칩 성장까지도 한국 메모리 기업의 장기 성장 동력으로 작용할 수 있음\n\n[ 주요 내용 ]\n\n- 5월 12일 트럼프가 에어포스 1 비행 중 젠슨 황에게 직접 전화해 알래스카 앵커리지에서 태운 것은 대통령이 반도체 의제를 정상회담의 핵심 딜로 인식한다는 강력한 신호\n\n- 2025년 12월부터 2026년 4월까지 추적한 타임라인은 미국의 조건부 수출 승인과 중국의 수입 차단이 동시에 진행되어 H200 수출이 완전히 교착 상태에 빠졌음을 보여줌\n\n- 중국 매체들은 양국 정부가 모두 길을 막은 상황에서 젠슨 황의 투 페이스 전략을 분석했으며 워싱턴에는 국가안보를 강조하고 시장에는 수출 의지를 표현하는 이중 메시지 전송으로 평가\n\n- 트레이딩키와 호라이즌 인베스트먼트 분석에 따르면 단 한 번 방문으로 규제 레드라인을 완전히 바꿀 수는 없지만 H200 수출 승인 시점 단축이나 B300 규제 준수 경로 명확화 수준의 실무적 진전은 충분히 가능",
      "updated": "2026-05-14T09:48:02.688Z"
    }
  ]
}